{
	"@context": "https://schema.org",
	"@graph": [
		{
			"@type": "ProfessionalService",
			"@id": "https://labate.io/#professionalservice",
			"name": "Labate Group",
			"description": "The Labate Group delivers tier-1 marketing services to SMBs, proprietary and custom software to tech start-ups, and white glove/white label fulfillment to agencies.",
			"url": "https://labate.io/",
			"sameAs": [
				"https://labate.link/facebook",
				"https://labate.link/instagram",
				"https://labate.link/github",
				"https://labate.link/linkedin",
				"https://labate.link/twitter",
				"https://labate.link/youtube",
				"https://labate.link/linktree"
			],
			"logo": "https://uploads-ssl.webflow.com/617db0d9cb2380592804fbb6/61ec95e3839abe2885eec854_logo.svg",
			"image": "https://uploads-ssl.webflow.com/617db0d9cb2380592804fbb6/61ec95e3839abe2885eec854_logo.svg",
			"founder": {
				"@type": "Person",
				"name": "",
				"url": "",
				"sameAs": [
					""
				]
			},
			"foundingDate": "",
			"numberOfEmployees": "",
			"slogan": "Marketing, Software, Fulfillment",
			"alternateName": "Labate Group",
			"legalName": "Labate Group",
			"address": [
				{
					"@type": "PostalAddress",
					"streetAddress": "8 Wright Street, 1st Fl",
					"addressLocality": "Westport",
					"addressRegion": "CT",
					"addressCountry": "United States",
					"postalCode": "06880"
				},
				{
					"@type": "PostalAddress",
					"streetAddress": "4 Research Drive, 4th Fl",
					"addressLocality": "Shelton",
					"addressRegion": "CT",
					"addressCountry": "United States",
					"postalCode": "06484"
				},
				{
					"@type": "PostalAddress",
					"streetAddress": "500 W. Putnam Ave E. 4th Fl",
					"addressLocality": "Greenwich",
					"addressRegion": "CT",
					"addressCountry": "United States",
					"postalCode": "06880"
				}
			],
			"telephone": "203-907-5536",
			"priceRange": "$$$"
		},
		{
			"@type": "WebSite",
			"@id": "https://labate.io/#website",
			"url": "https://labate.io/",
			"name": "Labate Group",
			"description": "Labate.io is a tight-knit group of skilled professionals on a mission to help businesses and professionals expand their sphere of influence in Fairfield County, CT.",
			"publisher": {
				"@id": "https://labate.io/#professionalservice"
			},
			"potentialAction": [
				{
					"@type": "SearchAction",
					"target": {
						"@type": "EntryPoint",
						"urlTemplate": "https://labate.io/search?query={search_term_string}"
					},
					"query-input": "required name=search_term_string"
				}
			],
			"inLanguage": "en-US",
			"copyrightYear": "2022",
			"copyrightHolder": {
				"@id": "https://labate.io/#professionalservice"
			}
		},
		{
			"@type": "ImageObject",
			"@id": "https://labate.io/faqs/#primaryimage",
			"inLanguage": "en-US",
			"url": "https://uploads-ssl.webflow.com/617db0d9cb2380592804fbb6/61ef117c03254c55363a5c8a_Ed%20Villeda%20and%20Jake%20Labate%20at%20table.png",
			"contentUrl": "https://uploads-ssl.webflow.com/617db0d9cb2380592804fbb6/61ef117c03254c55363a5c8a_Ed%20Villeda%20and%20Jake%20Labate%20at%20table.png",
			"width": "600",
			"height": "315"
		},
		{
			"@type": "WebPage",
			"@id": "https://labate.io/faqs/#webpage",
			"url": "https://labate.io/faqs/",
			"name": "Labate Group | FAQs",
			"description": "Labate.io is a tight-knit group of skilled professionals on a mission to help businesses and professionals expand their sphere of influence in Fairfield County, CT.",
			"isPartOf": {
				"@id": "https://labate.io/#website"
			},
			"primaryImageOfPage": {
				"@id": "https://labate.io/faqs/#primaryimage"
			},
			"image": {
				"@id": "https://labate.io/faqs/#primaryimage"
			},
			"datePublished": "2022-01-27T13:47:25+00:00",
			"dateModified": "2022-01-28T11:38:03+00:00",
			"breadcrumb": {
				"@type": "BreadcrumbList",
				"itemListElement": [
					{
						"@type": "ListItem",
						"position": 1,
						"name": "Home",
						"item": "https://labate.io/"
					},
					{
						"@type": "ListItem",
						"position": 2,
						"name": "Labate Group | FAQs",
						"item": "https://labate.io/faqs/"
					}
				]
			},
			"potentialAction": [
				{
					"@type": "ReadAction",
					"target": [
						"https://labate.io/faqs/"
					]
				}
			],
			"inLanguage": "en-US",
			"copyrightYear": "2022",
			"copyrightHolder": {
				"@id": "https://labate.io/#professionalservice"
			}
		},
		{
			"@type": "WPHeader",
			"@id": "https://labate.io/#header",
			"headline": "Labate Group | FAQs",
			"cssSelector": "div.nav",
			"potentialAction": {
				"@type": "Action",
				"name": "Contact",
				"target": "https://labate.io/contact"
			},
			"isPartOf": {
				"@id": "https://labate.io/#website"
			}
		},
		{
			"@type": "WPFooter",
			"@id": "https://labate.io/#footer",
			"cssSelector": "footer.w-container",
			"copyrightYear": "2022",
			"publisher": {
				"@id": "https://labate.io/#professionalservice"
			},
			"copyrightHolder": {
				"@id": "https://labate.io/#professionalservice"
			},
			"isPartOf": {
				"@id": "https://labate.io/#website"
			}
		}
	]
}
